Assignmnets/Assignment1/codes/3/3.v
module EvenParity(
    input [7:0] data,
    output parity
);
    assign parity = ~^data;
endmodule

Assignmnets/Assignment1/codes/tb3.v
`timescale 1ns/1ps

module even_parity_tb;

    reg [7:0] data;
    wire parity;

    // Instantiate the DUT (Device Under Test)
    EvenParity uut (
        .data(data),
        .parity(parity)
    );

    initial begin
        $dumpfile("even_parity.vcd");
        $dumpvars(0, even_parity_tb);

        $display("Time\tData\t\tParity");
        $monitor("%0t\t%b\t%b", $time, data, parity);

        // Test cases
        data = 8'b00000000; #10; // 0 ones → parity = 0
        data = 8'b00000001; #10; // 1 one  → parity = 1
        data = 8'b00001111; #10; // 4 ones → parity = 0
        data = 8'b10101010; #10; // 4 ones → parity = 0
        data = 8'b11111111; #10; // 8 ones → parity = 0
        data = 8'b11111110; #10; // 7 ones → parity = 1
        data = 8'b10000000; #10; // 1 one  → parity = 1
        data = 8'b11000000; #10; // 2 ones → parity = 0

        $finish;
    end

endmodule

Assignmnets/Assignment1/codes/3/even_parity.vcd
$date
	Fri Apr 11 11:02:14 2025
$end
$version
	Icarus Verilog
$end
$timescale
	1ps
$end
$scope module even_parity_tb $end
$var wire 1 ! parity $end
$var reg 8 " data [7:0] $end
$scope module uut $end
$var wire 8 # data [7:0] $end
$var wire 1 ! parity $end
$upscope $end
$upscope $end
$enddefinitions $end
#0
$dumpvars
b0 #
b0 "
1!
$end
#10000
0!
b1 "
b1 #
#20000
1!
b1111 "
b1111 #
#30000
b10101010 "
b10101010 #
#40000
b11111111 "
b11111111 #
#50000
0!
b11111110 "
b11111110 #
#60000
b10000000 "
b10000000 #
#70000
1!
b11000000 "
b11000000 #
