Assignmnets/Assignment1/codes/2/2.v
module counter(
        input clk,input reset,input enable,output reg  [3:0]count
);

always @(posedge clk) begin
        if (reset)
                count<=4'b0000;
        if (enable)
                casez(count)
                        4'bzzz0:begin count[0]<=1;end
                        4'bzz01:begin count[1:0]<=2'b10;end
                        4'bz011:begin count[2:0]<=3'b100;end
                        4'b0111:begin count[3:0]<=4'b1000;end
                        4'b1111:begin count[3:0]<=4'b0000;end
                endcase
end
endmodule

Assignments/Assignment1/codes/2/counter_tb.v
`timescale 1ns/1ps

module counter_tb;

    reg clk;
    reg reset;
    reg enable;
    wire [3:0] count;

    counter uut (
        .clk(clk),
        .reset(reset),
        .enable(enable),
        .count(count)
    );

    always #5 clk = ~clk;

    initial begin
        $dumpfile("counter.vcd");
        $dumpvars(0, counter_tb);

        clk = 0;
        reset = 0;
        enable = 0;

        $monitor("Time=%0t | Reset=%b Enable=%b Count=%b", $time, reset, enable, count);

        #2 reset = 1;
        #10 reset = 0;

        enable = 1;
        #100;

        enable = 0;
        #20;

        enable = 1;
        #40;

        $finish;
    end

endmodule

Assignments/Assignment1/codes/2/counter.vcd
$date
	Fri Apr 11 10:56:29 2025
$end
$version
	Icarus Verilog
$end
$timescale
	1ps
$end
$scope module counter_tb $end
$var wire 4 ! count [3:0] $end
$var reg 1 " clk $end
$var reg 1 # enable $end
$var reg 1 $ reset $end
$scope module uut $end
$var wire 1 " clk $end
$var wire 1 # enable $end
$var wire 1 $ reset $end
$var reg 4 % count [3:0] $end
$upscope $end
$upscope $end
$enddefinitions $end
#0
$dumpvars
bx %
0$
0#
0"
bx !
$end
#2000
1$
#5000
b0 !
b0 %
1"
#10000
0"
#12000
1#
0$
#15000
b1 !
b1 %
1"
#20000
0"
#25000
b10 !
b10 %
1"
#30000
0"
#35000
b11 !
b11 %
1"
#40000
0"
#45000
b100 !
b100 %
1"
#50000
0"
#55000
b101 !
b101 %
1"
#60000
0"
#65000
b110 !
b110 %
1"
#70000
0"
#75000
b111 !
b111 %
1"
#80000
0"
#85000
b1000 !
b1000 %
1"
#90000
0"
#95000
b1001 !
b1001 %
1"
#100000
0"
#105000
b1010 !
b1010 %
1"
#110000
0"
#112000
0#
#115000
1"
#120000
0"
#125000
1"
#130000
0"
#132000
1#
#135000
b1011 !
b1011 %
1"
#140000
0"
#145000
b1100 !
b1100 %
1"
#150000
0"
#155000
b1101 !
b1101 %
1"
#160000
0"
#165000
b1110 !
b1110 %
1"
