Assignmnets/Assignment2/codes/3/3_nandcounter.v
`timescale 1ns/1ps
module RippleAdder(input [3:0]a,input [3:0]b,output [3:0] sum,output cout);
genvar i;
wire [4:0] c;
assign c[0]=0;
generate
	for(i=0;i<4;i=i+1)begin 
		bitadder adders(.a(a[i]),.b(b[i]),.sum(sum[i]),.cin(c[i]),.cout(c[i+1]));
	end
endgenerate
assign cout=c[4];
endmodule
module bitadder(input a,input b,input cin,output cout, output sum);
wire ws1;
xorgate w1(ws1,a,b);
xorgate w2(sum,cin,ws1);
wire wc1,wc2,wc3,wc4;
andgate ww1(wc1,a,b);
andgate ww2(wc2,b,cin);
andgate w3(wc3,cin,a);
orgate w4(wc4,wc1,wc2);
orgate w5(cout,wc4,wc3);

endmodule
module xorgate(output o,input a, input b);
wire w1,w2,w3;
nandgate ww1(w1,a,b);
nandgate ww2(w2,a,w1);
nandgate ww3(w3,b,w1);
nandgate ww4(o,w2,w3);
endmodule
module andgate(output o,input a,input b);
wire w1,w2;
nandgate ww1(w1,a,b);
nandgate ww2(w2,a,b);
nandgate ww3(o,w1,w2);
endmodule
module orgate(output o,input a,input b);
wire w1,w2;
nandgate ww1(w1,a,a);
nandgate ww2(w2,b,b);
nandgate ww3(o,w1,w2);
endmodule
module nandgate(output o,input a,input b);
assign #1 o=~(a&b); 
endmodule

Assignmnets/Assignment2/codes/3/3_test.v
`timescale 1ns/1ps

module test_RippleAdder;

reg [3:0]a,b;
wire [3:0] sum;
wire cout;

RippleAdder tisra(.a(a),.b(b),.sum(sum),.cout(cout));

initial begin
        $dumpfile("8bitadder.vcd");
        $dumpvars(0,tisra);
	
        $display("Time\ta\tb\tsum\tcout");
        $monitor("%0dns\t%b\t%b\t%b\t%b", $time, a,b, sum,cout);
        a=4'b0000;b=4'b0000;#20;
	a=4'b1111;b=4'b1111;#20;
	a=4'b1010;b=4'b1111;#20;
	a=4'b1011;b=4'b1110;#20;
	a=4'b0101;b=4'b1101;#20;

	$finish;
end
endmodule

Assignmnets/Assignment2/codes/3/8bitadder.vcd
$date
	Fri Apr 18 17:58:34 2025
$end
$version
	Icarus Verilog
$end
$timescale
	1ps
$end
$scope module test_RippleAdder $end
$scope module tisra $end
$var wire 4 ! a [3:0] $end
$var wire 4 " b [3:0] $end
$var wire 4 # sum [3:0] $end
$var wire 1 $ cout $end
$var wire 5 % c [4:0] $end
$scope begin genblk1[0] $end
$scope module adders $end
$var wire 1 & a $end
$var wire 1 ' b $end
$var wire 1 ( cin $end
$var wire 1 ) ws1 $end
$var wire 1 * wc4 $end
$var wire 1 + wc3 $end
$var wire 1 , wc2 $end
$var wire 1 - wc1 $end
$var wire 1 . sum $end
$var wire 1 / cout $end
$scope module w1 $end
$var wire 1 & a $end
$var wire 1 ' b $end
$var wire 1 0 w3 $end
$var wire 1 1 w2 $end
$var wire 1 2 w1 $end
$var wire 1 ) o $end
$scope module ww1 $end
$var wire 1 & a $end
$var wire 1 ' b $end
$var wire 1 2 o $end
$upscope $end
$scope module ww2 $end
$var wire 1 & a $end
$var wire 1 2 b $end
$var wire 1 1 o $end
$upscope $end
$scope module ww3 $end
$var wire 1 ' a $end
$var wire 1 2 b $end
$var wire 1 0 o $end
$upscope $end
$scope module ww4 $end
$var wire 1 1 a $end
$var wire 1 0 b $end
$var wire 1 ) o $end
$upscope $end
$upscope $end
$scope module w2 $end
$var wire 1 ( a $end
$var wire 1 ) b $end
$var wire 1 3 w3 $end
$var wire 1 4 w2 $end
$var wire 1 5 w1 $end
$var wire 1 . o $end
$scope module ww1 $end
$var wire 1 ( a $end
$var wire 1 ) b $end
$var wire 1 5 o $end
$upscope $end
$scope module ww2 $end
$var wire 1 ( a $end
$var wire 1 5 b $end
$var wire 1 4 o $end
$upscope $end
$scope module ww3 $end
$var wire 1 ) a $end
$var wire 1 5 b $end
$var wire 1 3 o $end
$upscope $end
$scope module ww4 $end
$var wire 1 4 a $end
$var wire 1 3 b $end
$var wire 1 . o $end
$upscope $end
$upscope $end
$scope module w3 $end
$var wire 1 ( a $end
$var wire 1 & b $end
$var wire 1 6 w2 $end
$var wire 1 7 w1 $end
$var wire 1 + o $end
$scope module ww1 $end
$var wire 1 ( a $end
$var wire 1 & b $end
$var wire 1 7 o $end
$upscope $end
$scope module ww2 $end
$var wire 1 ( a $end
$var wire 1 & b $end
$var wire 1 6 o $end
$upscope $end
$scope module ww3 $end
$var wire 1 7 a $end
$var wire 1 6 b $end
$var wire 1 + o $end
$upscope $end
$upscope $end
$scope module w4 $end
$var wire 1 8 w2 $end
$var wire 1 9 w1 $end
$var wire 1 * o $end
$var wire 1 , b $end
$var wire 1 - a $end
$scope module ww1 $end
$var wire 1 9 o $end
$var wire 1 - b $end
$var wire 1 - a $end
$upscope $end
$scope module ww2 $end
$var wire 1 8 o $end
$var wire 1 , b $end
$var wire 1 , a $end
$upscope $end
$scope module ww3 $end
$var wire 1 9 a $end
$var wire 1 8 b $end
$var wire 1 * o $end
$upscope $end
$upscope $end
$scope module w5 $end
$var wire 1 * a $end
$var wire 1 + b $end
$var wire 1 : w2 $end
$var wire 1 ; w1 $end
$var wire 1 / o $end
$scope module ww1 $end
$var wire 1 * a $end
$var wire 1 * b $end
$var wire 1 ; o $end
$upscope $end
$scope module ww2 $end
$var wire 1 + a $end
$var wire 1 + b $end
$var wire 1 : o $end
$upscope $end
$scope module ww3 $end
$var wire 1 ; a $end
$var wire 1 : b $end
$var wire 1 / o $end
$upscope $end
$upscope $end
$scope module ww1 $end
$var wire 1 & a $end
$var wire 1 ' b $end
$var wire 1 < w2 $end
$var wire 1 = w1 $end
$var wire 1 - o $end
$scope module ww1 $end
$var wire 1 & a $end
$var wire 1 ' b $end
$var wire 1 = o $end
$upscope $end
$scope module ww2 $end
$var wire 1 & a $end
$var wire 1 ' b $end
$var wire 1 < o $end
$upscope $end
$scope module ww3 $end
$var wire 1 = a $end
$var wire 1 < b $end
$var wire 1 - o $end
$upscope $end
$upscope $end
$scope module ww2 $end
$var wire 1 ' a $end
$var wire 1 ( b $end
$var wire 1 > w2 $end
$var wire 1 ? w1 $end
$var wire 1 , o $end
$scope module ww1 $end
$var wire 1 ' a $end
$var wire 1 ( b $end
$var wire 1 ? o $end
$upscope $end
$scope module ww2 $end
$var wire 1 ' a $end
$var wire 1 ( b $end
$var wire 1 > o $end
$upscope $end
$scope module ww3 $end
$var wire 1 ? a $end
$var wire 1 > b $end
$var wire 1 , o $end
$upscope $end
$upscope $end
$upscope $end
$upscope $end
$scope begin genblk1[1] $end
$scope module adders $end
$var wire 1 @ a $end
$var wire 1 A b $end
$var wire 1 B cin $end
$var wire 1 C ws1 $end
$var wire 1 D wc4 $end
$var wire 1 E wc3 $end
$var wire 1 F wc2 $end
$var wire 1 G wc1 $end
$var wire 1 H sum $end
$var wire 1 I cout $end
$scope module w1 $end
$var wire 1 @ a $end
$var wire 1 A b $end
$var wire 1 J w3 $end
$var wire 1 K w2 $end
$var wire 1 L w1 $end
$var wire 1 C o $end
$scope module ww1 $end
$var wire 1 @ a $end
$var wire 1 A b $end
$var wire 1 L o $end
$upscope $end
$scope module ww2 $end
$var wire 1 @ a $end
$var wire 1 L b $end
$var wire 1 K o $end
$upscope $end
$scope module ww3 $end
$var wire 1 A a $end
$var wire 1 L b $end
$var wire 1 J o $end
$upscope $end
$scope module ww4 $end
$var wire 1 K a $end
$var wire 1 J b $end
$var wire 1 C o $end
$upscope $end
$upscope $end
$scope module w2 $end
$var wire 1 B a $end
$var wire 1 C b $end
$var wire 1 M w3 $end
$var wire 1 N w2 $end
$var wire 1 O w1 $end
$var wire 1 H o $end
$scope module ww1 $end
$var wire 1 B a $end
$var wire 1 C b $end
$var wire 1 O o $end
$upscope $end
$scope module ww2 $end
$var wire 1 B a $end
$var wire 1 O b $end
$var wire 1 N o $end
$upscope $end
$scope module ww3 $end
$var wire 1 C a $end
$var wire 1 O b $end
$var wire 1 M o $end
$upscope $end
$scope module ww4 $end
$var wire 1 N a $end
$var wire 1 M b $end
$var wire 1 H o $end
$upscope $end
$upscope $end
$scope module w3 $end
$var wire 1 B a $end
$var wire 1 @ b $end
$var wire 1 P w2 $end
$var wire 1 Q w1 $end
$var wire 1 E o $end
$scope module ww1 $end
$var wire 1 B a $end
$var wire 1 @ b $end
$var wire 1 Q o $end
$upscope $end
$scope module ww2 $end
$var wire 1 B a $end
$var wire 1 @ b $end
$var wire 1 P o $end
$upscope $end
$scope module ww3 $end
$var wire 1 Q a $end
$var wire 1 P b $end
$var wire 1 E o $end
$upscope $end
$upscope $end
$scope module w4 $end
$var wire 1 R w2 $end
$var wire 1 S w1 $end
$var wire 1 D o $end
$var wire 1 F b $end
$var wire 1 G a $end
$scope module ww1 $end
$var wire 1 S o $end
$var wire 1 G b $end
$var wire 1 G a $end
$upscope $end
$scope module ww2 $end
$var wire 1 R o $end
$var wire 1 F b $end
$var wire 1 F a $end
$upscope $end
$scope module ww3 $end
$var wire 1 S a $end
$var wire 1 R b $end
$var wire 1 D o $end
$upscope $end
$upscope $end
$scope module w5 $end
$var wire 1 D a $end
$var wire 1 E b $end
$var wire 1 T w2 $end
$var wire 1 U w1 $end
$var wire 1 I o $end
$scope module ww1 $end
$var wire 1 D a $end
$var wire 1 D b $end
$var wire 1 U o $end
$upscope $end
$scope module ww2 $end
$var wire 1 E a $end
$var wire 1 E b $end
$var wire 1 T o $end
$upscope $end
$scope module ww3 $end
$var wire 1 U a $end
$var wire 1 T b $end
$var wire 1 I o $end
$upscope $end
$upscope $end
$scope module ww1 $end
$var wire 1 @ a $end
$var wire 1 A b $end
$var wire 1 V w2 $end
$var wire 1 W w1 $end
$var wire 1 G o $end
$scope module ww1 $end
$var wire 1 @ a $end
$var wire 1 A b $end
$var wire 1 W o $end
$upscope $end
$scope module ww2 $end
$var wire 1 @ a $end
$var wire 1 A b $end
$var wire 1 V o $end
$upscope $end
$scope module ww3 $end
$var wire 1 W a $end
$var wire 1 V b $end
$var wire 1 G o $end
$upscope $end
$upscope $end
$scope module ww2 $end
$var wire 1 A a $end
$var wire 1 B b $end
$var wire 1 X w2 $end
$var wire 1 Y w1 $end
$var wire 1 F o $end
$scope module ww1 $end
$var wire 1 A a $end
$var wire 1 B b $end
$var wire 1 Y o $end
$upscope $end
$scope module ww2 $end
$var wire 1 A a $end
$var wire 1 B b $end
$var wire 1 X o $end
$upscope $end
$scope module ww3 $end
$var wire 1 Y a $end
$var wire 1 X b $end
$var wire 1 F o $end
$upscope $end
$upscope $end
$upscope $end
$upscope $end
$scope begin genblk1[2] $end
$scope module adders $end
$var wire 1 Z a $end
$var wire 1 [ b $end
$var wire 1 \ cin $end
$var wire 1 ] ws1 $end
$var wire 1 ^ wc4 $end
$var wire 1 _ wc3 $end
$var wire 1 ` wc2 $end
$var wire 1 a wc1 $end
$var wire 1 b sum $end
$var wire 1 c cout $end
$scope module w1 $end
$var wire 1 Z a $end
$var wire 1 [ b $end
$var wire 1 d w3 $end
$var wire 1 e w2 $end
$var wire 1 f w1 $end
$var wire 1 ] o $end
$scope module ww1 $end
$var wire 1 Z a $end
$var wire 1 [ b $end
$var wire 1 f o $end
$upscope $end
$scope module ww2 $end
$var wire 1 Z a $end
$var wire 1 f b $end
$var wire 1 e o $end
$upscope $end
$scope module ww3 $end
$var wire 1 [ a $end
$var wire 1 f b $end
$var wire 1 d o $end
$upscope $end
$scope module ww4 $end
$var wire 1 e a $end
$var wire 1 d b $end
$var wire 1 ] o $end
$upscope $end
$upscope $end
$scope module w2 $end
$var wire 1 \ a $end
$var wire 1 ] b $end
$var wire 1 g w3 $end
$var wire 1 h w2 $end
$var wire 1 i w1 $end
$var wire 1 b o $end
$scope module ww1 $end
$var wire 1 \ a $end
$var wire 1 ] b $end
$var wire 1 i o $end
$upscope $end
$scope module ww2 $end
$var wire 1 \ a $end
$var wire 1 i b $end
$var wire 1 h o $end
$upscope $end
$scope module ww3 $end
$var wire 1 ] a $end
$var wire 1 i b $end
$var wire 1 g o $end
$upscope $end
$scope module ww4 $end
$var wire 1 h a $end
$var wire 1 g b $end
$var wire 1 b o $end
$upscope $end
$upscope $end
$scope module w3 $end
$var wire 1 \ a $end
$var wire 1 Z b $end
$var wire 1 j w2 $end
$var wire 1 k w1 $end
$var wire 1 _ o $end
$scope module ww1 $end
$var wire 1 \ a $end
$var wire 1 Z b $end
$var wire 1 k o $end
$upscope $end
$scope module ww2 $end
$var wire 1 \ a $end
$var wire 1 Z b $end
$var wire 1 j o $end
$upscope $end
$scope module ww3 $end
$var wire 1 k a $end
$var wire 1 j b $end
$var wire 1 _ o $end
$upscope $end
$upscope $end
$scope module w4 $end
$var wire 1 l w2 $end
$var wire 1 m w1 $end
$var wire 1 ^ o $end
$var wire 1 ` b $end
$var wire 1 a a $end
$scope module ww1 $end
$var wire 1 m o $end
$var wire 1 a b $end
$var wire 1 a a $end
$upscope $end
$scope module ww2 $end
$var wire 1 l o $end
$var wire 1 ` b $end
$var wire 1 ` a $end
$upscope $end
$scope module ww3 $end
$var wire 1 m a $end
$var wire 1 l b $end
$var wire 1 ^ o $end
$upscope $end
$upscope $end
$scope module w5 $end
$var wire 1 ^ a $end
$var wire 1 _ b $end
$var wire 1 n w2 $end
$var wire 1 o w1 $end
$var wire 1 c o $end
$scope module ww1 $end
$var wire 1 ^ a $end
$var wire 1 ^ b $end
$var wire 1 o o $end
$upscope $end
$scope module ww2 $end
$var wire 1 _ a $end
$var wire 1 _ b $end
$var wire 1 n o $end
$upscope $end
$scope module ww3 $end
$var wire 1 o a $end
$var wire 1 n b $end
$var wire 1 c o $end
$upscope $end
$upscope $end
$scope module ww1 $end
$var wire 1 Z a $end
$var wire 1 [ b $end
$var wire 1 p w2 $end
$var wire 1 q w1 $end
$var wire 1 a o $end
$scope module ww1 $end
$var wire 1 Z a $end
$var wire 1 [ b $end
$var wire 1 q o $end
$upscope $end
$scope module ww2 $end
$var wire 1 Z a $end
$var wire 1 [ b $end
$var wire 1 p o $end
$upscope $end
$scope module ww3 $end
$var wire 1 q a $end
$var wire 1 p b $end
$var wire 1 a o $end
$upscope $end
$upscope $end
$scope module ww2 $end
$var wire 1 [ a $end
$var wire 1 \ b $end
$var wire 1 r w2 $end
$var wire 1 s w1 $end
$var wire 1 ` o $end
$scope module ww1 $end
$var wire 1 [ a $end
$var wire 1 \ b $end
$var wire 1 s o $end
$upscope $end
$scope module ww2 $end
$var wire 1 [ a $end
$var wire 1 \ b $end
$var wire 1 r o $end
$upscope $end
$scope module ww3 $end
$var wire 1 s a $end
$var wire 1 r b $end
$var wire 1 ` o $end
$upscope $end
$upscope $end
$upscope $end
$upscope $end
$scope begin genblk1[3] $end
$scope module adders $end
$var wire 1 t a $end
$var wire 1 u b $end
$var wire 1 v cin $end
$var wire 1 w ws1 $end
$var wire 1 x wc4 $end
$var wire 1 y wc3 $end
$var wire 1 z wc2 $end
$var wire 1 { wc1 $end
$var wire 1 | sum $end
$var wire 1 } cout $end
$scope module w1 $end
$var wire 1 t a $end
$var wire 1 u b $end
$var wire 1 ~ w3 $end
$var wire 1 !" w2 $end
$var wire 1 "" w1 $end
$var wire 1 w o $end
$scope module ww1 $end
$var wire 1 t a $end
$var wire 1 u b $end
$var wire 1 "" o $end
$upscope $end
$scope module ww2 $end
$var wire 1 t a $end
$var wire 1 "" b $end
$var wire 1 !" o $end
$upscope $end
$scope module ww3 $end
$var wire 1 u a $end
$var wire 1 "" b $end
$var wire 1 ~ o $end
$upscope $end
$scope module ww4 $end
$var wire 1 !" a $end
$var wire 1 ~ b $end
$var wire 1 w o $end
$upscope $end
$upscope $end
$scope module w2 $end
$var wire 1 v a $end
$var wire 1 w b $end
$var wire 1 #" w3 $end
$var wire 1 $" w2 $end
$var wire 1 %" w1 $end
$var wire 1 | o $end
$scope module ww1 $end
$var wire 1 v a $end
$var wire 1 w b $end
$var wire 1 %" o $end
$upscope $end
$scope module ww2 $end
$var wire 1 v a $end
$var wire 1 %" b $end
$var wire 1 $" o $end
$upscope $end
$scope module ww3 $end
$var wire 1 w a $end
$var wire 1 %" b $end
$var wire 1 #" o $end
$upscope $end
$scope module ww4 $end
$var wire 1 $" a $end
$var wire 1 #" b $end
$var wire 1 | o $end
$upscope $end
$upscope $end
$scope module w3 $end
$var wire 1 v a $end
$var wire 1 t b $end
$var wire 1 &" w2 $end
$var wire 1 '" w1 $end
$var wire 1 y o $end
$scope module ww1 $end
$var wire 1 v a $end
$var wire 1 t b $end
$var wire 1 '" o $end
$upscope $end
$scope module ww2 $end
$var wire 1 v a $end
$var wire 1 t b $end
$var wire 1 &" o $end
$upscope $end
$scope module ww3 $end
$var wire 1 '" a $end
$var wire 1 &" b $end
$var wire 1 y o $end
$upscope $end
$upscope $end
$scope module w4 $end
$var wire 1 (" w2 $end
$var wire 1 )" w1 $end
$var wire 1 x o $end
$var wire 1 z b $end
$var wire 1 { a $end
$scope module ww1 $end
$var wire 1 )" o $end
$var wire 1 { b $end
$var wire 1 { a $end
$upscope $end
$scope module ww2 $end
$var wire 1 (" o $end
$var wire 1 z b $end
$var wire 1 z a $end
$upscope $end
$scope module ww3 $end
$var wire 1 )" a $end
$var wire 1 (" b $end
$var wire 1 x o $end
$upscope $end
$upscope $end
$scope module w5 $end
$var wire 1 x a $end
$var wire 1 y b $end
$var wire 1 *" w2 $end
$var wire 1 +" w1 $end
$var wire 1 } o $end
$scope module ww1 $end
$var wire 1 x a $end
$var wire 1 x b $end
$var wire 1 +" o $end
$upscope $end
$scope module ww2 $end
$var wire 1 y a $end
$var wire 1 y b $end
$var wire 1 *" o $end
$upscope $end
$scope module ww3 $end
$var wire 1 +" a $end
$var wire 1 *" b $end
$var wire 1 } o $end
$upscope $end
$upscope $end
$scope module ww1 $end
$var wire 1 t a $end
$var wire 1 u b $end
$var wire 1 ," w2 $end
$var wire 1 -" w1 $end
$var wire 1 { o $end
$scope module ww1 $end
$var wire 1 t a $end
$var wire 1 u b $end
$var wire 1 -" o $end
$upscope $end
$scope module ww2 $end
$var wire 1 t a $end
$var wire 1 u b $end
$var wire 1 ," o $end
$upscope $end
$scope module ww3 $end
$var wire 1 -" a $end
$var wire 1 ," b $end
$var wire 1 { o $end
$upscope $end
$upscope $end
$scope module ww2 $end
$var wire 1 u a $end
$var wire 1 v b $end
$var wire 1 ." w2 $end
$var wire 1 /" w1 $end
$var wire 1 z o $end
$scope module ww1 $end
$var wire 1 u a $end
$var wire 1 v b $end
$var wire 1 /" o $end
$upscope $end
$scope module ww2 $end
$var wire 1 u a $end
$var wire 1 v b $end
$var wire 1 ." o $end
$upscope $end
$scope module ww3 $end
$var wire 1 /" a $end
$var wire 1 ." b $end
$var wire 1 z o $end
$upscope $end
$upscope $end
$upscope $end
$upscope $end
$upscope $end
$upscope $end
$enddefinitions $end
#0
$dumpvars
x/"
x."
x-"
x,"
x+"
x*"
x)"
x("
x'"
x&"
x%"
x$"
x#"
x""
x!"
x~
x}
x|
x{
xz
xy
xx
xw
xv
0u
0t
xs
xr
xq
xp
xo
xn
xm
xl
xk
xj
xi
xh
xg
xf
xe
xd
xc
xb
xa
x`
x_
x^
x]
x\
0[
0Z
xY
xX
xW
xV
xU
xT
xS
xR
xQ
xP
xO
xN
xM
xL
xK
xJ
xI
xH
xG
xF
xE
xD
xC
xB
0A
0@
x?
x>
x=
x<
x;
x:
x9
x8
x7
x6
x5
x4
x3
x2
x1
x0
x/
x.
x-
x,
x+
x*
x)
0(
0'
0&
bx0 %
x$
bx #
b0 "
b0 !
$end
#1000
10
1J
1Y
1X
1d
1s
1r
1~
1/"
1."
12
11
1=
1<
1L
1K
1Q
1P
1W
1V
1f
1e
1k
1j
1q
1p
1""
1!"
1'"
1&"
1-"
1,"
1>
1?
16
17
14
15
#2000
0F
0`
0z
0)
0-
0C
0E
0G
0]
0_
0a
0w
0y
0{
0,
0+
#3000
1R
1l
1("
13
19
1O
1M
1T
1S
1i
1g
1n
1m
1%"
1#"
1*"
1)"
18
1:
#4000
bx0 #
0.
0D
0^
0x
0*
#5000
1U
1o
1+"
1;
#6000
0\
0v
0$
0B
0I
0c
0}
b0 %
0/
#7000
1h
1$"
1N
#8000
0b
0|
b0 #
0H
#20000
1'
1A
1[
1u
1&
1@
1Z
1t
b1111 "
b1111 !
#21000
00
0J
0d
0~
02
01
0=
0<
0L
0K
0W
0V
0f
0e
0q
0p
0""
0!"
0-"
0,"
#22000
11
10
1)
1-
1K
1J
1C
1G
1e
1d
1]
1a
1!"
1~
1w
1{
#23000
0)
03
09
0C
0M
0S
0]
0g
0m
0w
0#"
0)"
#24000
13
1.
1*
1M
1H
1D
1g
1b
1^
1#"
b1111 #
1|
1x
#25000
0.
0;
0H
0U
0b
0o
b0 #
0|
0+"
#26000
1B
1\
1v
1$
1/
1I
1c
b11110 %
1}
#27000
0N
0Q
0P
0Y
0X
0h
0k
0j
0s
0r
0$"
0'"
0&"
0/"
0."
#28000
1H
1E
1F
1b
1_
1`
b1110 #
1|
1y
1z
#29000
0T
0R
0n
0l
0*"
0("
#40000
0&
0Z
b1010 !
#41000
12
1=
1<
1f
1k
1j
1q
1p
#42000
00
0-
0d
0_
0a
#43000
1)
19
1]
1n
1m
#44000
03
0*
0i
0g
#45000
b1111 #
1.
1;
1h
1g
#46000
0B
b11100 %
0/
b1011 #
0b
#47000
1N
1Q
1P
1Y
1X
#48000
b1001 #
0H
0E
0F
#49000
1T
1R
#60000
0'
1&
b1110 "
b1011 !
#61000
10
01
#80000
1'
0A
0@
1Z
0t
b1101 "
b101 !
#81000
02
00
0=
0<
1L
1W
1V
0f
0e
0k
0j
0q
0p
1""
1'"
1&"
1-"
1,"
#82000
11
10
1-
0G
1e
1d
1_
1a
0~
0y
0{
#83000
0)
09
1S
0]
0n
0m
1w
1*"
1)"
#84000
13
1*
0D
1i
0%"
0#"
#85000
b1000 #
0.
0;
1U
0h
1$"
1#"
#86000
1B
0\
1/
b11010 %
0I
1b
b100 #
0|
#87000
0N
1h
1k
1j
1s
1r
#88000
1H
b10 #
0b
0_
0`
#89000
1n
1l
