Assignmnets/Assignment1/codes/1.v
module encoder(
	input [3:0] in,output reg [1:0] out,output reg valid
);
always @(*) begin
casez (in)
	4'b1zzz: begin out = 2'b11; valid = 1; end
	4'b01zz: begin out = 2'b10; valid = 1; end
        4'b001z: begin out = 2'b01; valid = 1; end
        4'b0001: begin out = 2'b00; valid = 1; end
        default: begin out = 2'b00; valid = 0; end
endcase
end
endmodule

Assignments/Assignment1/codes/1/1tb.v
`timescale 1ns/1ps

module encoder_tb;

    reg [3:0] in;
    wire [1:0] out;
    wire valid;

    // Instantiate the encoder module
    encoder uut (
        .in(in),
        .out(out),
        .valid(valid)
    );

    initial begin
        $dumpfile("encoder.vcd");
        $dumpvars(0, encoder_tb);

        $display("Time\tin\tout\tvalid");
        $monitor("%0t\t%b\t%b\t%b", $time, in, out, valid);

        // Test all combinations from 4'b0000 to 4'b1111
        in = 4'b0000; #10;
        in = 4'b0001; #10;
        in = 4'b0010; #10;
        in = 4'b0011; #10;
        in = 4'b0100; #10;
        in = 4'b0101; #10;
        in = 4'b0110; #10;
        in = 4'b0111; #10;
        in = 4'b1000; #10;
        in = 4'b1001; #10;
        in = 4'b1010; #10;
        in = 4'b1011; #10;
        in = 4'b1100; #10;
        in = 4'b1101; #10;
        in = 4'b1110; #10;
        in = 4'b1111; #10;

        $finish;
    end

endmodule

Assignmnets/Assignment1/codes/encoder.vcd
$date
	Fri Apr 11 11:05:03 2025
$end
$version
	Icarus Verilog
$end
$timescale
	1ps
$end
$scope module encoder_tb $end
$var wire 1 ! valid $end
$var wire 2 " out [1:0] $end
$var reg 4 # in [3:0] $end
$scope module uut $end
$var wire 4 $ in [3:0] $end
$var reg 2 % out [1:0] $end
$var reg 1 ! valid $end
$upscope $end
$upscope $end
$enddefinitions $end
#0
$dumpvars
b0 %
b0 $
b0 #
b0 "
0!
$end
#10000
1!
b1 #
b1 $
#20000
b1 "
b1 %
b10 #
b10 $
#30000
b11 #
b11 $
#40000
b10 "
b10 %
b100 #
b100 $
#50000
b101 #
b101 $
#60000
b110 #
b110 $
#70000
b111 #
b111 $
#80000
b11 "
b11 %
b1000 #
b1000 $
#90000
b1001 #
b1001 $
#100000
b1010 #
b1010 $
#110000
b1011 #
b1011 $
#120000
b1100 #
b1100 $
#130000
b1101 #
b1101 $
#140000
b1110 #
b1110 $
#150000
b1111 #
b1111 $
